originpy/__init__.py
originpy/hello.py
originpy-0.0.2.dist-info/LICENSE
originpy-0.0.2.dist-info/METADATA
originpy-0.0.2.dist-info/WHEEL
originpy-0.0.2.dist-info/top_level.txt
originpy-0.0.2.dist-info/RECORD
