Metadata-Version: 2.1
Name: originpy
Version: 0.0.2
Summary: Plot on origin automatically
Author: Shaohan Tian
Author-email: <shaohan.tian@hotmail.com>
License: UNKNOWN
Keywords: python,test,orginpy
Platform: UNKNOWN
Classifier: Development Status :: 1 - Planning
Classifier: Intended Audience :: Developers
Classifier: Programming Language :: Python :: 3
Classifier: Operating System :: Unix
Classifier: Operating System :: MacOS :: MacOS X
Classifier: Operating System :: Microsoft :: Windows
License-File: LICENSE
Requires-Dist: originpro
Requires-Dist: numpy
Requires-Dist: pandas
